{"duration":192,"records":[{"duration":45,"stepId":"io.quarkus.deployment.steps.MainClassBuildStep#build","started":"16:00:57.038","dependents":[],"id":377,"thread":"build-10"},{"duration":33,"stepId":"io.quarkus.arc.deployment.ArcProcessor#generateResources","started":"16:00:56.973","dependents":[346,350,369,349,376,373,367,359,345,360,347,377,348],"id":344,"thread":"build-22"},{"duration":22,"stepId":"io.quarkus.deployment.ide.IdeProcessor#detectRunningIdeProcesses","started":"16:00:56.910","dependents":[288],"id":287,"thread":"build-21"},{"duration":21,"stepId":"io.quarkus.deployment.steps.ClassTransformingBuildStep#handleClassTransformation","started":"16:00:57.009","dependents":[370],"id":369,"thread":"build-24"},{"duration":20,"stepId":"io.quarkus.vertx.http.deployment.devmode.console.DevConsoleProcessor#setupDeploymentSideHandling","started":"16:00:57.017","dependents":[372,374,373],"id":371,"thread":"build-3"},{"duration":19,"stepId":"io.quarkus.arc.deployment.ArcProcessor#registerBeans","started":"16:00:56.938","dependents":[322,313,324,312,321,323,315,311,317,320,314,316,318],"id":310,"thread":"build-15"},{"duration":14,"stepId":"io.quarkus.deployment.steps.ConfigDescriptionBuildStep#createConfigDescriptions","started":"16:00:56.900","dependents":[371,308],"id":187,"thread":"build-13"},{"duration":10,"stepId":"io.quarkus.arc.deployment.BeanArchiveProcessor#build","started":"16:00:56.925","dependents":[350,300,322,349,321,305,299,306,303,358,301,304,360],"id":298,"thread":"build-2"},{"duration":9,"stepId":"io.quarkus.vertx.http.deployment.devmode.console.DevConsoleProcessor#collectTemplates","started":"16:00:56.893","dependents":[371],"id":117,"thread":"build-4"},{"duration":9,"stepId":"io.quarkus.arc.deployment.ArcProcessor#validate","started":"16:00:56.961","dependents":[330,335,369,342,333,331,343,338,344,332,337,334],"id":329,"thread":"build-15"},{"duration":7,"stepId":"io.quarkus.vertx.http.deployment.webjar.WebJarProcessor#processWebJarDevMode","started":"16:00:56.900","dependents":[377,309],"id":132,"thread":"build-3"},{"duration":7,"stepId":"io.quarkus.arc.deployment.devconsole.ArcDevConsoleProcessor#collectBeanInfo","started":"16:00:56.971","dependents":[366],"id":343,"thread":"build-20"},{"duration":6,"stepId":"io.quarkus.vertx.core.deployment.VertxCoreProcessor#createVertxThreadFactory","started":"16:00:56.900","dependents":[125,377],"id":124,"thread":"build-14"},{"duration":6,"stepId":"io.quarkus.vertx.core.deployment.VertxCoreProcessor#createVertxContextHandlers","started":"16:00:56.900","dependents":[126,125,377],"id":121,"thread":"build-9"},{"duration":5,"stepId":"io.quarkus.hibernate.orm.deployment.HibernateOrmProcessor#enhancerDomainObjects","started":"16:00:56.960","dependents":[369,328,327],"id":326,"thread":"build-21"},{"duration":4,"stepId":"io.quarkus.vertx.http.deployment.HttpSecurityProcessor#initBasicAuth","started":"16:00:56.902","dependents":[317,320,323,377],"id":122,"thread":"build-2"},{"duration":4,"stepId":"io.quarkus.vertx.http.deployment.devmode.console.ConfigEditorProcessor#config","started":"16:00:56.935","dependents":[371,374,357,377,309],"id":308,"thread":"build-13"},{"duration":4,"stepId":"io.quarkus.resteasy.reactive.server.deployment.ResteasyReactiveScanningProcessor#handleCustomAnnotatedMethods","started":"16:00:56.920","dependents":[298,283,280,306],"id":277,"thread":"build-20"},{"duration":4,"stepId":"io.quarkus.deployment.steps.BannerProcessor#recordBanner","started":"16:00:56.902","dependents":[292,377],"id":119,"thread":"build-8"},{"duration":4,"stepId":"io.quarkus.vertx.core.deployment.VertxCoreProcessor#eventLoopCount","started":"16:00:56.902","dependents":[375,377],"id":120,"thread":"build-15"},{"duration":3,"stepId":"io.quarkus.vertx.http.deployment.devmode.tests.TestsProcessor#toggleTestRunner","started":"16:00:56.895","dependents":[371,309],"id":55,"thread":"build-3"},{"duration":3,"stepId":"io.quarkus.netty.deployment.NettyProcessor#registerQualifiers","started":"16:00:56.895","dependents":[298,306],"id":58,"thread":"build-2"},{"duration":3,"stepId":"io.quarkus.resteasy.reactive.server.deployment.ResteasyReactiveProcessor#setupDeployment","started":"16:00:57.013","dependents":[371,376,361,377,365,362],"id":360,"thread":"build-13"},{"duration":3,"stepId":"io.quarkus.deployment.steps.ConfigGenerationBuildStep#checkForBuildTimeConfigChange","started":"16:00:56.908","dependents":[377],"id":175,"thread":"build-9"},{"duration":3,"stepId":"io.quarkus.resteasy.reactive.server.deployment.ResteasyReactiveProcessor#serverSerializers","started":"16:00:57.010","dependents":[376,360,377],"id":359,"thread":"build-29"},{"duration":3,"stepId":"io.quarkus.vertx.http.deployment.devmode.console.DevConsoleProcessor#setupDevConsoleRoutes","started":"16:00:56.940","dependents":[371,361,377,365],"id":309,"thread":"build-20"},{"duration":2,"stepId":"io.quarkus.deployment.dev.HotDeploymentWatchedFileBuildStep#setupWatchedFileHotDeployment","started":"16:00:56.924","dependents":[372,374,373],"id":286,"thread":"build-20"},{"duration":2,"stepId":"io.quarkus.resteasy.reactive.server.deployment.ResteasyReactiveProcessor#setupEndpoints","started":"16:00:57.007","dependents":[358,369,376,360,355,377,353,351],"id":350,"thread":"build-21"},{"duration":2,"stepId":"io.quarkus.hibernate.orm.deployment.HibernateOrmProcessor#build_7a4403d699506d83ac39616f3c11e5e1b448d863","started":"16:00:56.923","dependents":[344,377],"id":285,"thread":"build-22"},{"duration":2,"stepId":"io.quarkus.deployment.steps.BootstrapConfigSetupBuildStep#setupBootstrapConfig","started":"16:00:56.899","dependents":[377,113],"id":110,"thread":"build-2"},{"duration":2,"stepId":"io.quarkus.vertx.core.deployment.VertxCoreProcessor#build_9fb3ce360263cc99d07c9172ec2feeaa85afcc1a","started":"16:00:56.908","dependents":[372,319,174,373,168,375,367,323,317,374,320,365,377,348],"id":165,"thread":"build-15"},{"duration":1,"stepId":"io.quarkus.hibernate.orm.deployment.HibernateOrmCdiProcessor#generateDataSourceBeans","started":"16:00:56.923","dependents":[317,298,320,323,377,306],"id":281,"thread":"build-4"},{"duration":1,"stepId":"io.quarkus.hibernate.orm.deployment.HibernateOrmProcessor#defineJpaEntities","started":"16:00:56.921","dependents":[274,285,278,273,282,376,326,370,270,286,347,271],"id":269,"thread":"build-25"},{"duration":1,"stepId":"io.quarkus.vertx.http.deployment.devmode.ArcDevProcessor#registerRoutes","started":"16:00:56.971","dependents":[371,363,364,344,361,377,365],"id":342,"thread":"build-21"},{"duration":1,"stepId":"io.quarkus.agroal.deployment.AgroalProcessor#generateDataSourceSupportBean","started":"16:00:56.918","dependents":[317,298,320,323,377,306],"id":241,"thread":"build-7"},{"duration":1,"stepId":"io.quarkus.deployment.steps.ApplicationIndexBuildStep#build","started":"16:00:56.909","dependents":[350,188,306,166,315],"id":164,"thread":"build-14"},{"duration":1,"stepId":"io.quarkus.datasource.deployment.devservices.DevUIDatasourceProcessor#devConsoleInfo","started":"16:00:56.900","dependents":[366],"id":111,"thread":"build-8"},{"duration":1,"stepId":"io.quarkus.vertx.http.deployment.VertxHttpProcessor#finalizeRouter","started":"16:00:57.018","dependents":[372,374,368,373,377],"id":367,"thread":"build-29"},{"duration":1,"stepId":"io.quarkus.deployment.logging.LoggingResourceProcessor#setupLoggingRuntimeInit","started":"16:00:56.933","dependents":[371,293,377,309],"id":292,"thread":"build-22"},{"duration":1,"stepId":"io.quarkus.vertx.http.deployment.devmode.ArcDevProcessor#eventsEndpoint","started":"16:00:56.892","dependents":[371,377,309],"id":26,"thread":"build-4"},{"duration":1,"stepId":"io.quarkus.agroal.deployment.AgroalProcessor#generateDataSourceBeans","started":"16:00:56.918","dependents":[273,317,320,242,281,347,323,377],"id":240,"thread":"build-20"},{"duration":1,"stepId":"io.quarkus.vertx.http.deployment.StaticResourcesProcessor#collectStaticResources","started":"16:00:56.915","dependents":[348],"id":193,"thread":"build-13"},{"duration":1,"stepId":"io.quarkus.arc.deployment.SplitPackageProcessor#splitPackageDetection","started":"16:00:56.915","dependents":[344],"id":194,"thread":"build-17"},{"duration":1,"stepId":"io.quarkus.datasource.deployment.devservices.DevUIDatasourceProcessor#devConsoleCleanDatabaseHandler","started":"16:00:56.892","dependents":[371,377,309],"id":29,"thread":"build-2"},{"duration":1,"stepId":"io.quarkus.arc.deployment.SyntheticBeansProcessor#initRegular","started":"16:00:56.958","dependents":[324],"id":323,"thread":"build-4"},{"duration":1,"stepId":"io.quarkus.vertx.http.deployment.devmode.ArcDevProcessor#invocationsEndpoint","started":"16:00:56.893","dependents":[371,377,309],"id":31,"thread":"build-6"},{"duration":1,"stepId":"io.quarkus.deployment.steps.ThreadPoolSetup#createExecutor","started":"16:00:56.906","dependents":[126,367,140,377,127,165],"id":125,"thread":"build-4"},{"duration":1,"stepId":"io.quarkus.hibernate.orm.deployment.HibernateOrmProcessor#build_daeea4f2c9416db083cc1423ec1bf5c757ad2a16","started":"16:00:56.923","dependents":[328,377],"id":278,"thread":"build-16"},{"duration":1,"stepId":"io.quarkus.arc.deployment.SyntheticBeansProcessor#initRuntime","started":"16:00:56.958","dependents":[372,374,324,373,347,377],"id":320,"thread":"build-15"},{"duration":1,"stepId":"io.quarkus.resteasy.reactive.server.deployment.devconsole.ResteasyReactiveDevConsoleProcessor#collectStaticResourcesInfo","started":"16:00:56.915","dependents":[366],"id":192,"thread":"build-15"},{"duration":1,"stepId":"io.quarkus.vertx.http.deployment.VertxHttpProcessor#bodyHandler","started":"16:00:56.908","dependents":[367,377],"id":160,"thread":"build-10"},{"duration":1,"stepId":"io.quarkus.hibernate.orm.deployment.HibernateOrmProcessor#jpaEntitiesIndexer","started":"16:00:56.919","dependents":[370,269],"id":262,"thread":"build-22"},{"duration":1,"stepId":"io.quarkus.arc.deployment.staticmethods.InterceptedStaticMethodsProcessor#collectInterceptedStaticMethods","started":"16:00:56.958","dependents":[322,329,345],"id":321,"thread":"build-21"},{"duration":1,"stepId":"io.quarkus.vertx.http.deployment.devmode.console.DevConsoleProcessor#buildTimeTemplates","started":"16:00:57.017","dependents":[372,374,373],"id":366,"thread":"build-10"},{"duration":1,"stepId":"io.quarkus.deployment.dev.testing.TestTracingProcessor#testConsoleCommand","started":"16:00:56.919","dependents":[357],"id":266,"thread":"build-24"},{"duration":0,"stepId":"io.quarkus.panache.common.deployment.PanacheHibernateCommonResourceProcessor#findEntityClasses","started":"16:00:56.922","dependents":[327],"id":272,"thread":"build-25"},{"duration":0,"stepId":"io.quarkus.resteasy.reactive.server.deployment.ResteasyReactiveProcessor#integrateEagerSecurity","started":"16:00:56.918","dependents":[350],"id":231,"thread":"build-10"},{"duration":0,"stepId":"io.quarkus.resteasy.reactive.common.deployment.ResteasyReactiveCommonProcessor#deprioritizeLegacyProviders","started":"16:00:56.917","dependents":[359],"id":202,"thread":"build-12"},{"duration":0,"stepId":"io.quarkus.vertx.http.deployment.devmode.console.DevConsoleProcessor#builder","started":"16:00:56.932","dependents":[371,309],"id":289,"thread":"build-21"},{"duration":0,"stepId":"io.quarkus.datasource.deployment.DataSourcesExcludedFromHealthChecksProcessor#produceBean","started":"16:00:56.914","dependents":[317,320,323,377],"id":180,"thread":"build-15"},{"duration":0,"stepId":"io.quarkus.vertx.http.deployment.devmode.console.DevConsoleProcessor#setupConsole","started":"16:00:56.910","dependents":[372,374,373],"id":170,"thread":"build-12"},{"duration":0,"stepId":"io.quarkus.arc.deployment.BuildTimeEnabledProcessor#unlessBuildProperty","started":"16:00:56.919","dependents":[260,249,263],"id":247,"thread":"build-16"},{"duration":0,"stepId":"io.quarkus.vertx.deployment.VertxProcessor#registerVerticleClasses","started":"16:00:56.919","dependents":[376],"id":239,"thread":"build-2"},{"duration":0,"stepId":"io.quarkus.hibernate.orm.deployment.HibernateOrmProcessor#parsePersistenceXmlDescriptors","started":"16:00:56.909","dependents":[156,273,242],"id":155,"thread":"build-7"},{"duration":0,"stepId":"io.quarkus.deployment.steps.ReflectiveHierarchyStep#ignoreJavaClassWarnings","started":"16:00:56.917","dependents":[353],"id":199,"thread":"build-1"},{"duration":0,"stepId":"io.quarkus.deployment.steps.ConfigGenerationBuildStep#suppressNonRuntimeConfigChanged","started":"16:00:56.899","dependents":[175],"id":75,"thread":"build-1"},{"duration":0,"stepId":"io.quarkus.resteasy.reactive.server.deployment.ResteasyReactiveDevModeProcessor#openCommand","started":"16:00:57.009","dependents":[357],"id":355,"thread":"build-14"},{"duration":0,"stepId":"io.quarkus.deployment.steps.ConfigGenerationBuildStep#staticInitSources","started":"16:00:56.900","dependents":[336],"id":92,"thread":"build-3"},{"duration":0,"stepId":"io.quarkus.deployment.steps.NativeImageResourcesStep#registerPackageResources","started":"16:00:56.893","dependents":[341],"id":15,"thread":"build-5"},{"duration":0,"stepId":"io.quarkus.resteasy.reactive.jackson.deployment.processor.ResteasyReactiveJacksonProcessor#handleJsonAnnotations","started":"16:00:57.009","dependents":[376,354,377],"id":352,"thread":"build-21"},{"duration":0,"stepId":"io.quarkus.hibernate.orm.deployment.HibernateOrmProcessor#handleMoveSql","started":"16:00:56.900","dependents":[374],"id":109,"thread":"build-11"},{"duration":0,"stepId":"io.quarkus.deployment.JniProcessor#setupJni","started":"16:00:56.902","dependents":[220],"id":112,"thread":"build-15"},{"duration":0,"stepId":"io.quarkus.arc.deployment.devconsole.ArcDevConsoleProcessor#monitor","started":"16:00:56.915","dependents":[374,298,306],"id":190,"thread":"build-20"},{"duration":0,"stepId":"io.quarkus.resteasy.reactive.server.deployment.ResteasyReactiveCDIProcessor#additionalBeans","started":"16:00:56.921","dependents":[298,376,306],"id":268,"thread":"build-24"},{"duration":0,"stepId":"io.quarkus.hibernate.orm.deployment.HibernateOrmProcessor#registerBeans","started":"16:00:56.925","dependents":[298,329,306],"id":282,"thread":"build-2"},{"duration":0,"stepId":"io.quarkus.deployment.steps.ConfigGenerationBuildStep#buildTimeRunTimeConfig","started":"16:00:56.900","dependents":[341],"id":106,"thread":"build-5"},{"duration":0,"stepId":"io.quarkus.deployment.steps.ConfigGenerationBuildStep#runtimeDefaultsConfig","started":"16:00:56.971","dependents":[341],"id":340,"thread":"build-19"},{"duration":0,"stepId":"io.quarkus.resteasy.reactive.server.deployment.ResteasyReactiveVertxWebSocketIntegrationProcessor#scanner","started":"16:00:56.899","dependents":[350],"id":63,"thread":"build-10"},{"duration":0,"stepId":"io.quarkus.resteasy.reactive.server.deployment.ResteasyReactiveScanningProcessor#defaultUnwrappedException","started":"16:00:56.917","dependents":[283],"id":208,"thread":"build-2"},{"duration":0,"stepId":"io.quarkus.netty.deployment.NettyProcessor#build","started":"16:00:56.908","dependents":[376,220],"id":130,"thread":"build-7"},{"duration":0,"stepId":"io.quarkus.arc.deployment.SyntheticBeansProcessor#initStatic","started":"16:00:56.958","dependents":[324,377],"id":317,"thread":"build-22"},{"duration":0,"stepId":"io.quarkus.deployment.console.ConsoleProcessor#setupConsole","started":"16:00:56.908","dependents":[291,144,293,290],"id":128,"thread":"build-14"},{"duration":0,"stepId":"io.quarkus.smallrye.context.deployment.SmallRyeContextPropagationProcessor#buildStatic","started":"16:00:56.899","dependents":[377],"id":89,"thread":"build-13"},{"duration":0,"stepId":"io.quarkus.deployment.console.ConsoleProcessor#installCliCommands","started":"16:00:57.009","dependents":[372,374,373],"id":357,"thread":"build-21"},{"duration":0,"stepId":"io.quarkus.vertx.core.deployment.VertxCoreProcessor#cleanupVertxWarnings","started":"16:00:56.909","dependents":[292,216],"id":145,"thread":"build-4"},{"duration":0,"stepId":"io.quarkus.hibernate.orm.panache.common.deployment.PanacheJpaCommonResourceProcessor#lookupNamedQueries_5a86a91ed8ef1aa483288c8239df231983eeb766","started":"16:00:56.922","dependents":[275],"id":271,"thread":"build-22"},{"duration":0,"stepId":"io.quarkus.arc.deployment.UnremovableAnnotationsProcessor#unremovableBeans","started":"16:00:56.917","dependents":[329],"id":204,"thread":"build-10"},{"duration":0,"stepId":"io.quarkus.arc.deployment.ArcProcessor#loggerProducer","started":"16:00:56.899","dependents":[298,306],"id":67,"thread":"build-9"},{"duration":0,"stepId":"io.quarkus.resteasy.reactive.server.deployment.ResteasyReactiveProcessor#vertxIntegration","started":"16:00:56.893","dependents":[359,358,356],"id":23,"thread":"build-3"},{"duration":0,"stepId":"io.quarkus.arc.deployment.BuildTimeEnabledProcessor#buildExclusions","started":"16:00:56.921","dependents":[264],"id":263,"thread":"build-22"},{"duration":0,"stepId":"io.quarkus.arc.deployment.configproperties.ConfigPropertiesBuildStep#produceConfigPropertiesMetadata","started":"16:00:56.921","dependents":[265],"id":264,"thread":"build-16"},{"duration":0,"stepId":"io.quarkus.arc.deployment.ConfigBuildStep#additionalBeans","started":"16:00:56.893","dependents":[298,306],"id":19,"thread":"build-8"},{"duration":0,"stepId":"io.quarkus.hibernate.orm.deployment.HibernateOrmProcessor#startPersistenceUnits","started":"16:00:57.007","dependents":[372,374,373,377],"id":347,"thread":"build-24"},{"duration":0,"stepId":"io.quarkus.resteasy.reactive.server.deployment.ResteasyReactiveCDIProcessor#contextInjection","started":"16:00:56.900","dependents":[302,298,306,303],"id":104,"thread":"build-12"},{"duration":0,"stepId":"io.quarkus.hibernate.orm.deployment.HibernateOrmProcessor#setupPersistenceProvider","started":"16:00:56.914","dependents":[183,347,377],"id":182,"thread":"build-17"},{"duration":0,"stepId":"io.quarkus.vertx.http.deployment.devmode.tests.TestsProcessor#runFailedTests","started":"16:00:56.899","dependents":[371,309],"id":79,"thread":"build-9"},{"duration":0,"stepId":"io.quarkus.deployment.steps.ConfigGenerationBuildStep#setupConfigOverride","started":"16:00:56.892","dependents":[],"id":2,"thread":"build-2"},{"duration":0,"stepId":"io.quarkus.jackson.deployment.JacksonProcessor#register","started":"16:00:56.918","dependents":[298,376,353,306],"id":236,"thread":"build-15"},{"duration":0,"stepId":"io.quarkus.jsonp.deployment.JsonpProcessor#build","started":"16:00:56.909","dependents":[376,377],"id":148,"thread":"build-4"},{"duration":0,"stepId":"io.quarkus.resteasy.reactive.server.deployment.ResteasyReactiveScanningProcessor#scanForParamConverters_dcdfdd2a310a09abe5ee3f0ed2b2bc49f36f3d07","started":"16:00:56.920","dependents":[350,298,376,360,306],"id":259,"thread":"build-15"},{"duration":0,"stepId":"io.quarkus.resteasy.reactive.jackson.deployment.processor.ResteasyReactiveJacksonProcessor#exceptionMappers","started":"16:00:56.917","dependents":[283],"id":200,"thread":"build-6"},{"duration":0,"stepId":"io.quarkus.deployment.console.ConsoleProcessor#setupExceptionHandler","started":"16:00:56.932","dependents":[291],"id":290,"thread":"build-22"},{"duration":0,"stepId":"io.quarkus.deployment.steps.ProfileBuildStep#defaultProfile","started":"16:00:56.917","dependents":[340],"id":201,"thread":"build-13"},{"duration":0,"stepId":"io.quarkus.hibernate.orm.deployment.ResteasyReactiveServerIntegrationProcessor#unwrappedExceptions","started":"16:00:56.900","dependents":[283],"id":90,"thread":"build-10"},{"duration":0,"stepId":"io.quarkus.deployment.CollectionClassProcessor#setupCollectionClasses","started":"16:00:56.894","dependents":[376],"id":36,"thread":"build-9"},{"duration":0,"stepId":"io.quarkus.deployment.steps.NativeImageFeatureStep#generateNativeResourcesList","started":"16:00:56.972","dependents":[],"id":341,"thread":"build-22"},{"duration":0,"stepId":"io.quarkus.vertx.http.deployment.devmode.tests.TestsProcessor#setupTestRoutes","started":"16:00:56.908","dependents":[371,144,361,377,365],"id":143,"thread":"build-3"},{"duration":0,"stepId":"io.quarkus.jackson.deployment.JacksonProcessor#supportMixins","started":"16:00:56.918","dependents":[317,320,376,323,377],"id":225,"thread":"build-1"},{"duration":0,"stepId":"io.quarkus.resteasy.reactive.server.deployment.ResteasyReactiveProcessor#handleClassLevelExceptionMappers","started":"16:00:56.920","dependents":[350,376],"id":254,"thread":"build-15"},{"duration":0,"stepId":"io.quarkus.deployment.steps.CurateOutcomeBuildStep#removeResources","started":"16:00:56.909","dependents":[369],"id":150,"thread":"build-4"},{"duration":0,"stepId":"io.quarkus.arc.deployment.ConfigBuildStep#validateConfigMappingsInjectionPoints","started":"16:00:56.971","dependents":[339,336],"id":333,"thread":"build-25"},{"duration":0,"stepId":"io.quarkus.vertx.http.deployment.VertxHttpProcessor#preinitializeRouter","started":"16:00:56.910","dependents":[317,320,323,377,365],"id":174,"thread":"build-17"},{"duration":0,"stepId":"io.quarkus.arc.deployment.ConfigBuildStep#registerConfigMappingConverters","started":"16:00:56.918","dependents":[376],"id":224,"thread":"build-12"},{"duration":0,"stepId":"io.quarkus.hibernate.orm.deployment.HibernateOrmProcessor#defineTypeOfImpliedPU","started":"16:00:56.919","dependents":[273,276,281],"id":242,"thread":"build-5"},{"duration":0,"stepId":"io.quarkus.arc.deployment.ConfigBuildStep#vetoMPConfigProperties","started":"16:00:56.918","dependents":[306],"id":210,"thread":"build-22"},{"duration":0,"stepId":"io.quarkus.deployment.steps.MainClassBuildStep#applicationReflection","started":"16:00:56.899","dependents":[376],"id":76,"thread":"build-11"},{"duration":0,"stepId":"io.quarkus.arc.deployment.TestsAsBeansProcessor#testAnnotations","started":"16:00:56.899","dependents":[298,190,306],"id":56,"thread":"build-7"},{"duration":0,"stepId":"io.quarkus.smallrye.context.deployment.SmallRyeContextPropagationProcessor#registerBean","started":"16:00:56.893","dependents":[298,306],"id":20,"thread":"build-3"},{"duration":0,"stepId":"io.quarkus.arc.deployment.ConfigBuildStep#registerConfigClasses","started":"16:00:56.972","dependents":[377],"id":339,"thread":"build-22"},{"duration":0,"stepId":"io.quarkus.vertx.http.deployment.devmode.tests.TestsProcessor#results","started":"16:00:56.900","dependents":[366],"id":84,"thread":"build-1"},{"duration":0,"stepId":"io.quarkus.arc.deployment.HotDeploymentConfigBuildStep#startup","started":"16:00:56.909","dependents":[171],"id":146,"thread":"build-12"},{"duration":0,"stepId":"io.quarkus.deployment.ide.IdeProcessor#effectiveIde","started":"16:00:56.932","dependents":[291,371,289,290],"id":288,"thread":"build-20"},{"duration":0,"stepId":"io.quarkus.deployment.steps.AdditionalClassLoaderResourcesBuildStep#appendAdditionalClassloaderResources","started":"16:00:56.893","dependents":[221],"id":17,"thread":"build-3"},{"duration":0,"stepId":"io.quarkus.hibernate.orm.deployment.HibernateOrmCdiProcessor#convertJpaResourceAnnotationsToQualifier","started":"16:00:56.923","dependents":[306],"id":276,"thread":"build-15"},{"duration":0,"stepId":"io.quarkus.resteasy.reactive.common.deployment.ResteasyReactiveCommonProcessor#resourceIndex","started":"16:00:56.919","dependents":[298,250,351],"id":246,"thread":"build-2"},{"duration":0,"stepId":"io.quarkus.hibernate.orm.deployment.HibernateOrmProcessor#candidatesForFieldAccess","started":"16:00:56.922","dependents":[272],"id":270,"thread":"build-13"},{"duration":0,"stepId":"io.quarkus.arc.deployment.ReflectiveBeanClassesProcessor#implicitReflectiveBeanClasses","started":"16:00:56.958","dependents":[344],"id":314,"thread":"build-4"},{"duration":0,"stepId":"io.quarkus.arc.deployment.staticmethods.InterceptedStaticMethodsProcessor#callInitializer","started":"16:00:57.007","dependents":[377],"id":345,"thread":"build-12"},{"duration":0,"stepId":"io.quarkus.vertx.deployment.VertxProcessor#collectEventConsumers","started":"16:00:56.958","dependents":[319,324],"id":318,"thread":"build-25"},{"duration":0,"stepId":"io.quarkus.deployment.logging.LoggingResourceProcessor#setupLoggingStaticInit","started":"16:00:56.900","dependents":[377],"id":96,"thread":"build-13"},{"duration":0,"stepId":"io.quarkus.resteasy.reactive.server.deployment.ResteasyReactiveCDIProcessor#beanDefiningAnnotations","started":"16:00:56.899","dependents":[298,190,306],"id":64,"thread":"build-8"},{"duration":0,"stepId":"io.quarkus.netty.deployment.NettyProcessor#limitArenaSize","started":"16:00:56.900","dependents":[377],"id":98,"thread":"build-7"},{"duration":0,"stepId":"io.quarkus.vertx.deployment.VertxProcessor#unremovableBeans","started":"16:00:56.909","dependents":[329],"id":152,"thread":"build-8"},{"duration":0,"stepId":"io.quarkus.arc.deployment.ArcProcessor#validateAsyncObserverExceptionHandlers","started":"16:00:56.971","dependents":[344],"id":331,"thread":"build-16"},{"duration":0,"stepId":"io.quarkus.vertx.http.deployment.HttpSecurityProcessor#builtins","started":"16:00:56.900","dependents":[298,181,306],"id":97,"thread":"build-8"},{"duration":0,"stepId":"io.quarkus.arc.deployment.configproperties.ConfigPropertiesBuildStep#setup","started":"16:00:56.921","dependents":[346,298,376,340],"id":265,"thread":"build-22"},{"duration":0,"stepId":"io.quarkus.resteasy.reactive.server.deployment.devconsole.ResteasyReactiveDevConsoleProcessor#exceptionMappers","started":"16:00:56.909","dependents":[374],"id":153,"thread":"build-3"},{"duration":0,"stepId":"io.quarkus.deployment.console.ConsoleProcessor#helpCommand","started":"16:00:56.895","dependents":[357],"id":46,"thread":"build-10"},{"duration":0,"stepId":"io.quarkus.deployment.steps.CompiledJavaVersionBuildStep#compiledJavaVersion","started":"16:00:56.899","dependents":[350],"id":74,"thread":"build-5"},{"duration":0,"stepId":"io.quarkus.deployment.index.ApplicationArchiveBuildStep#addConfiguredIndexedDependencies","started":"16:00:56.911","dependents":[188],"id":172,"thread":"build-20"},{"duration":0,"stepId":"io.quarkus.resteasy.reactive.server.deployment.ResteasyReactiveProcessor#setMinimalNettyMaxOrderSize","started":"16:00:56.899","dependents":[130,98],"id":71,"thread":"build-12"},{"duration":0,"stepId":"io.quarkus.arc.deployment.TestsAsBeansProcessor#testClassBeans","started":"16:00:56.899","dependents":[298,306],"id":65,"thread":"build-5"},{"duration":0,"stepId":"io.quarkus.deployment.steps.ConfigGenerationBuildStep#watchConfigFiles","started":"16:00:56.909","dependents":[286],"id":154,"thread":"build-5"},{"duration":0,"stepId":"io.quarkus.arc.deployment.ArcProcessor#quarkusApplication","started":"16:00:56.918","dependents":[298,306],"id":229,"thread":"build-6"},{"duration":0,"stepId":"io.quarkus.vertx.http.deployment.devmode.console.DevConsoleProcessor#setupWebJar","started":"16:00:56.893","dependents":[132],"id":25,"thread":"build-3"},{"duration":0,"stepId":"io.quarkus.vertx.http.deployment.VertxHttpProcessor#httpRoot","started":"16:00:56.910","dependents":[364,355,170,367,169],"id":167,"thread":"build-10"},{"duration":0,"stepId":"io.quarkus.jdbc.h2.deployment.JDBCH2Processor#configureAgroalConnection","started":"16:00:56.914","dependents":[298,306],"id":177,"thread":"build-9"},{"duration":0,"stepId":"io.quarkus.deployment.ide.IdeProcessor#detectIdeFiles","started":"16:00:56.895","dependents":[288],"id":49,"thread":"build-8"},{"duration":0,"stepId":"io.quarkus.arc.deployment.ConfigBuildStep#registerConfigRootsAsBeans","started":"16:00:56.900","dependents":[317,320,323],"id":100,"thread":"build-11"},{"duration":0,"stepId":"io.quarkus.smallrye.context.deployment.SmallRyeContextPropagationProcessor#createSynthBeansForConfiguredInjectionPoints","started":"16:00:56.958","dependents":[317,320,323,377],"id":316,"thread":"build-16"},{"duration":0,"stepId":"io.quarkus.arc.deployment.ArcProcessor#marker","started":"16:00:56.895","dependents":[188],"id":37,"thread":"build-3"},{"duration":0,"stepId":"io.quarkus.resteasy.reactive.server.deployment.ResteasyReactiveProcessor#unremovableBeans","started":"16:00:56.920","dependents":[329],"id":258,"thread":"build-4"},{"duration":0,"stepId":"io.quarkus.deployment.ExtensionLoader#config","started":"16:00:56.900","dependents":[372,109,112,132,120,94,227,367,125,97,279,315,264,114,144,282,183,98,365,292,108,278,249,119,373,96,188,180,302,99,100,231,118,344,181,340,116,377,194,107,111,350,187,174,217,333,305,338,122,103,293,106,375,182,235,115,101,165,306,163,175,190,348,362,336,298,369,342,128,218,240,131,368,150,141,164,134,129,160,273,130,288,161,133,172,173,360,167],"id":86,"thread":"build-1"},{"duration":0,"stepId":"io.quarkus.hibernate.orm.panache.deployment.PanacheHibernateResourceProcessor#produceModel","started":"16:00:56.893","dependents":[326,262],"id":16,"thread":"build-1"},{"duration":0,"stepId":"io.quarkus.arc.deployment.ArcProcessor#quarkusMain","started":"16:00:56.895","dependents":[298,190,306],"id":42,"thread":"build-6"},{"duration":0,"stepId":"io.quarkus.deployment.logging.LoggingResourceProcessor#setProperty","started":"16:00:56.908","dependents":[377],"id":139,"thread":"build-16"},{"duration":0,"stepId":"io.quarkus.jdbc.h2.deployment.JDBCH2Processor#devDbHandler","started":"16:00:56.892","dependents":[293],"id":8,"thread":"build-1"},{"duration":0,"stepId":"io.quarkus.vertx.http.deployment.devmode.BuildMetricsDevConsoleProcessor#collectMetrics","started":"16:00:56.917","dependents":[366],"id":212,"thread":"build-9"},{"duration":0,"stepId":"io.quarkus.narayana.jta.deployment.NarayanaJtaProcessor#transactionContext","started":"16:00:56.938","dependents":[310],"id":307,"thread":"build-20"},{"duration":0,"stepId":"io.quarkus.resteasy.reactive.jackson.deployment.processor.ResteasyReactiveJacksonProcessor#additionalProviders","started":"16:00:57.009","dependents":[359,358,356],"id":354,"thread":"build-24"},{"duration":0,"stepId":"io.quarkus.smallrye.context.deployment.SmallRyeContextPropagationProcessor#transformInjectionPoint","started":"16:00:56.909","dependents":[306],"id":147,"thread":"build-3"},{"duration":0,"stepId":"io.quarkus.hibernate.orm.deployment.HibernateOrmProcessor#contributePersistenceXmlToJpaModel","started":"16:00:56.910","dependents":[269],"id":156,"thread":"build-5"},{"duration":0,"stepId":"io.quarkus.deployment.steps.RegisterForReflectionBuildStep#build","started":"16:00:56.918","dependents":[376],"id":230,"thread":"build-19"},{"duration":0,"stepId":"io.quarkus.jdbc.h2.deployment.H2JDBCReflections#build","started":"16:00:56.899","dependents":[376],"id":59,"thread":"build-8"},{"duration":0,"stepId":"io.quarkus.arc.deployment.AutoInjectFieldProcessor#autoInjectQualifiers","started":"16:00:56.936","dependents":[302,303],"id":301,"thread":"build-22"},{"duration":0,"stepId":"io.quarkus.vertx.deployment.VertxProcessor#autoAddScope","started":"16:00:56.899","dependents":[303],"id":73,"thread":"build-11"},{"duration":0,"stepId":"io.quarkus.vertx.http.deployment.VertxHttpProcessor#hostDefault","started":"16:00:56.899","dependents":[62],"id":60,"thread":"build-5"},{"duration":0,"stepId":"io.quarkus.resteasy.reactive.server.deployment.devconsole.ResteasyReactiveDevConsoleProcessor#collectScores","started":"16:00:56.914","dependents":[374],"id":184,"thread":"build-24"},{"duration":0,"stepId":"io.quarkus.deployment.steps.BannerProcessor#watchBannerChanges","started":"16:00:56.910","dependents":[286],"id":163,"thread":"build-17"},{"duration":0,"stepId":"io.quarkus.resteasy.reactive.server.deployment.ResteasyReactiveProcessor#responseHeaderSupport","started":"16:00:56.893","dependents":[350],"id":10,"thread":"build-5"},{"duration":0,"stepId":"io.quarkus.vertx.http.deployment.VertxHttpProcessor#additionalBeans","started":"16:00:56.893","dependents":[298,306],"id":13,"thread":"build-1"},{"duration":0,"stepId":"io.quarkus.arc.deployment.ArcProcessor#exposeCustomScopeNames","started":"16:00:56.895","dependents":[298,305,190,306,61,303,315],"id":52,"thread":"build-8"},{"duration":0,"stepId":"io.quarkus.jdbc.h2.deployment.JDBCH2Processor#registerDriver","started":"16:00:56.910","dependents":[217],"id":162,"thread":"build-10"},{"duration":0,"stepId":"io.quarkus.resteasy.reactive.common.deployment.ResteasyReactiveCommonProcessor#scanResources","started":"16:00:56.919","dependents":[350,254,277,349,352,360,258,253,306,252],"id":250,"thread":"build-9"},{"duration":0,"stepId":"io.quarkus.deployment.logging.LoggingResourceProcessor#setUpDarkeningDefault","started":"16:00:56.893","dependents":[340],"id":21,"thread":"build-7"},{"duration":0,"stepId":"io.quarkus.resteasy.reactive.server.deployment.ResteasyReactiveScanningProcessor#scanForFeatures","started":"16:00:56.920","dependents":[360,268],"id":256,"thread":"build-7"},{"duration":0,"stepId":"io.quarkus.hibernate.orm.deployment.HibernateOrmProcessor#produceLoggingCategories","started":"16:00:56.906","dependents":[123],"id":118,"thread":"build-16"},{"duration":0,"stepId":"io.quarkus.deployment.steps.CombinedIndexBuildStep#build","started":"16:00:56.917","dependents":[261,232,222,227,255,237,238,264,282,328,223,265,262,230,249,239,312,225,283,233,251,231,257,332,335,352,236,248,272,224,235,229,306,226,277,228,247,256,267,234,244,246,313,327,353,271,273,245,266,243],"id":221,"thread":"build-5"},{"duration":0,"stepId":"io.quarkus.arc.deployment.ArcProcessor#registerSyntheticObservers","started":"16:00:56.960","dependents":[325,329,376,344],"id":324,"thread":"build-15"},{"duration":0,"stepId":"io.quarkus.deployment.steps.ReflectiveHierarchyStep#build","started":"16:00:57.009","dependents":[376],"id":353,"thread":"build-29"},{"duration":0,"stepId":"io.quarkus.deployment.steps.ShutdownListenerBuildStep#setupShutdown","started":"16:00:57.019","dependents":[377],"id":368,"thread":"build-10"},{"duration":0,"stepId":"io.quarkus.deployment.dev.IsolatedDevModeMain$5$1@7a71a0fa","started":"16:00:56.909","dependents":[350,306],"id":149,"thread":"build-14"},{"duration":0,"stepId":"io.quarkus.hibernate.orm.deployment.HibernateOrmProcessor#multitenancy","started":"16:00:56.925","dependents":[317,320,329,323,377],"id":284,"thread":"build-13"},{"duration":0,"stepId":"io.quarkus.vertx.deployment.EventBusCodecProcessor#registerCodecs","started":"16:00:56.936","dependents":[319,376],"id":300,"thread":"build-21"},{"duration":0,"stepId":"io.quarkus.hibernate.orm.deployment.HibernateOrmProcessor#contributeQuarkusConfigToJpaModel","started":"16:00:56.908","dependents":[269],"id":131,"thread":"build-16"},{"duration":0,"stepId":"io.quarkus.arc.deployment.BuildTimeEnabledProcessor#ifBuildProfile","started":"16:00:56.918","dependents":[260,249,263],"id":226,"thread":"build-3"},{"duration":0,"stepId":"io.quarkus.deployment.steps.DevModeBuildStep#watchChanges","started":"16:00:56.901","dependents":[286],"id":107,"thread":"build-7"},{"duration":0,"stepId":"io.quarkus.resteasy.reactive.server.deployment.ResteasyReactiveProcessor#addAllWriteableMarker","started":"16:00:57.009","dependents":[369],"id":356,"thread":"build-14"},{"duration":0,"stepId":"io.quarkus.deployment.dev.testing.TestTracingProcessor#handle","started":"16:00:56.895","dependents":[292,216],"id":54,"thread":"build-5"},{"duration":0,"stepId":"io.quarkus.arc.deployment.WrongAnnotationUsageProcessor#detect","started":"16:00:56.958","dependents":[344],"id":315,"thread":"build-22"},{"duration":0,"stepId":"io.quarkus.resteasy.reactive.common.deployment.ResteasyReactiveCommonProcessor#setupEndpoints","started":"16:00:57.007","dependents":[359,358,376,356],"id":349,"thread":"build-14"},{"duration":0,"stepId":"io.quarkus.resteasy.reactive.common.deployment.ResteasyReactiveCommonProcessor#buildResourceInterceptors","started":"16:00:56.924","dependents":[298,360,306],"id":280,"thread":"build-16"},{"duration":0,"stepId":"io.quarkus.vertx.core.deployment.VertxCoreProcessor#build_9d6b7122fb368970c50c3a870d1f672392cd8afb","started":"16:00:56.910","dependents":[341,376,220],"id":157,"thread":"build-2"},{"duration":0,"stepId":"io.quarkus.deployment.dev.ConfigureDisableInstrumentationBuildStep#configure","started":"16:00:56.911","dependents":[372,374,373],"id":171,"thread":"build-22"},{"duration":0,"stepId":"io.quarkus.deployment.logging.LoggingWithPanacheProcessor#process","started":"16:00:56.918","dependents":[369],"id":222,"thread":"build-23"},{"duration":0,"stepId":"io.quarkus.arc.deployment.ConfigBuildStep#registerCustomConfigBeanTypes","started":"16:00:56.958","dependents":[317,320,376,323],"id":311,"thread":"build-2"},{"duration":0,"stepId":"io.quarkus.arc.deployment.BuildTimeEnabledProcessor#conditionTransformer","started":"16:00:56.920","dependents":[306],"id":260,"thread":"build-2"},{"duration":0,"stepId":"io.quarkus.smallrye.context.deployment.SmallRyeContextPropagationProcessor#build","started":"16:00:56.908","dependents":[317,320,323,377],"id":140,"thread":"build-2"},{"duration":0,"stepId":"io.quarkus.vertx.http.deployment.HttpSecurityProcessor#setupAuthenticationMechanisms","started":"16:00:56.914","dependents":[298,344,367,377,306],"id":181,"thread":"build-22"},{"duration":0,"stepId":"io.quarkus.resteasy.reactive.server.deployment.ResteasyReactiveProcessor#recordableConstructor","started":"16:00:56.917","dependents":[377],"id":206,"thread":"build-11"},{"duration":0,"stepId":"io.quarkus.datasource.deployment.devservices.DevServicesDatasourceProcessor#launchDatabases","started":"16:00:56.934","dependents":[294,296],"id":293,"thread":"build-21"},{"duration":0,"stepId":"io.quarkus.vertx.http.deployment.devmode.console.DevConsoleProcessor#config","started":"16:00:56.935","dependents":[366],"id":297,"thread":"build-21"},{"duration":0,"stepId":"io.quarkus.deployment.steps.CurateOutcomeBuildStep#curateOutcome","started":"16:00:56.900","dependents":[109,132,371,217,369,158,150,366,293,164,176,153,184,188,309,185,189,186,190,308],"id":103,"thread":"build-6"},{"duration":0,"stepId":"io.quarkus.jackson.deployment.JacksonProcessor#generateCustomizer","started":"16:00:56.919","dependents":[298],"id":248,"thread":"build-15"},{"duration":0,"stepId":"io.quarkus.resteasy.reactive.server.deployment.ResteasyReactiveProcessor#applyRuntimeConfig","started":"16:00:57.017","dependents":[377],"id":362,"thread":"build-10"},{"duration":0,"stepId":"io.quarkus.deployment.dev.testing.TestTracingProcessor#sharedStateListener","started":"16:00:56.892","dependents":[144],"id":5,"thread":"build-2"},{"duration":0,"stepId":"io.quarkus.vertx.http.deployment.devmode.console.DevConsoleProcessor#runtimeTemplates","started":"16:00:57.038","dependents":[377],"id":374,"thread":"build-24"},{"duration":0,"stepId":"io.quarkus.vertx.core.deployment.VertxCoreProcessor#doNotRemoveVertxOptionsCustomizers","started":"16:00:56.909","dependents":[329],"id":151,"thread":"build-16"},{"duration":0,"stepId":"io.quarkus.arc.deployment.ConfigBuildStep#registerConfigMappingsBean","started":"16:00:56.958","dependents":[324],"id":313,"thread":"build-20"},{"duration":0,"stepId":"io.quarkus.deployment.steps.NativeImageConfigBuildStep#build","started":"16:00:56.918","dependents":[377],"id":220,"thread":"build-17"},{"duration":0,"stepId":"io.quarkus.deployment.steps.ConfigGenerationBuildStep#extensionMappings","started":"16:00:56.918","dependents":[335,313,333,312,376,338],"id":235,"thread":"build-13"},{"duration":0,"stepId":"io.quarkus.jdbc.h2.deployment.JDBCH2Processor#registerDefaultDbType","started":"16:00:56.918","dependents":[217,293],"id":214,"thread":"build-17"},{"duration":0,"stepId":"io.quarkus.arc.deployment.ConfigBuildStep#validateConfigInjectionPoints","started":"16:00:56.971","dependents":[346],"id":330,"thread":"build-4"},{"duration":0,"stepId":"io.quarkus.deployment.logging.LoggingResourceProcessor#registerMetrics","started":"16:00:56.908","dependents":[292,377],"id":129,"thread":"build-5"},{"duration":0,"stepId":"io.quarkus.arc.deployment.devconsole.ArcDevConsoleProcessor#exposeArcContainer","started":"16:00:56.914","dependents":[374,377],"id":185,"thread":"build-17"},{"duration":0,"stepId":"io.quarkus.vertx.http.deployment.devmode.tests.TestsProcessor#toggleInstrumentation","started":"16:00:56.892","dependents":[371,309],"id":6,"thread":"build-3"},{"duration":0,"stepId":"io.quarkus.vertx.core.deployment.VertxCoreProcessor#preventLoggerContention","started":"16:00:56.895","dependents":[123],"id":40,"thread":"build-2"},{"duration":0,"stepId":"io.quarkus.hibernate.orm.deployment.HibernateOrmProcessor#configurationDescriptorBuilding","started":"16:00:56.922","dependents":[274,285,278,341,282,370,276,281,286,377,284,279],"id":273,"thread":"build-24"},{"duration":0,"stepId":"io.quarkus.deployment.ForkJoinPoolProcessor#setProperty","started":"16:00:56.894","dependents":[377],"id":33,"thread":"build-1"},{"duration":0,"stepId":"io.quarkus.vertx.http.deployment.devmode.tests.TestsProcessor#handleTestResult","started":"16:00:56.895","dependents":[371,309],"id":51,"thread":"build-2"},{"duration":0,"stepId":"io.quarkus.mutiny.deployment.MutinyProcessor#runtimeInit","started":"16:00:56.908","dependents":[377],"id":126,"thread":"build-14"},{"duration":0,"stepId":"io.quarkus.hibernate.orm.deployment.metrics.HibernateOrmMetricsProcessor#metrics","started":"16:00:56.914","dependents":[377],"id":183,"thread":"build-22"},{"duration":0,"stepId":"io.quarkus.agroal.deployment.AgroalProcessor#build","started":"16:00:56.918","dependents":[341,241,218,240,376,220],"id":217,"thread":"build-24"},{"duration":0,"stepId":"io.quarkus.arc.deployment.StartupBuildSteps#registerStartupObservers","started":"16:00:56.961","dependents":[329],"id":325,"thread":"build-4"},{"duration":0,"stepId":"io.quarkus.resteasy.reactive.server.deployment.ResteasyReactiveScanningProcessor#compressionSupport","started":"16:00:56.900","dependents":[350],"id":94,"thread":"build-3"},{"duration":0,"stepId":"io.quarkus.resteasy.reactive.server.deployment.ResteasyReactiveProcessor#generateCustomProducer","started":"16:00:56.920","dependents":[298,306],"id":252,"thread":"build-10"},{"duration":0,"stepId":"io.quarkus.deployment.steps.DevServicesConfigBuildStep#setup","started":"16:00:56.934","dependents":[372,374,373,295,340,296,308],"id":294,"thread":"build-22"},{"duration":0,"stepId":"io.quarkus.deployment.pkg.steps.JarResultBuildStep#outputTarget","started":"16:00:56.900","dependents":[102],"id":101,"thread":"build-3"},{"duration":0,"stepId":"io.quarkus.netty.deployment.NettyProcessor#setNettyMachineId","started":"16:00:56.893","dependents":[377],"id":32,"thread":"build-9"},{"duration":0,"stepId":"io.quarkus.vertx.http.deployment.devmode.tests.TestsProcessor#toggleTestOutput","started":"16:00:56.917","dependents":[371,309],"id":207,"thread":"build-1"},{"duration":0,"stepId":"io.quarkus.resteasy.reactive.jackson.deployment.processor.ResteasyReactiveJacksonProcessor#customExceptionMappers","started":"16:00:56.899","dependents":[277],"id":78,"thread":"build-6"},{"duration":0,"stepId":"io.quarkus.narayana.jta.deployment.NarayanaJtaProcessor#unremovableBean","started":"16:00:56.893","dependents":[329],"id":24,"thread":"build-5"},{"duration":0,"stepId":"io.quarkus.vertx.http.deployment.devmode.tests.TestsProcessor#runAllTests","started":"16:00:56.899","dependents":[371,309],"id":72,"thread":"build-6"},{"duration":0,"stepId":"io.quarkus.arc.deployment.ArcProcessor#launchMode","started":"16:00:56.893","dependents":[298,306],"id":11,"thread":"build-1"},{"duration":0,"stepId":"io.quarkus.resteasy.reactive.server.deployment.ResteasyReactiveScanningProcessor#asyncSupport","started":"16:00:56.893","dependents":[350],"id":22,"thread":"build-9"},{"duration":0,"stepId":"io.quarkus.deployment.index.ApplicationArchiveBuildStep#build","started":"16:00:56.914","dependents":[193,291,192,273,298,369,221,327,227,194,191,334],"id":188,"thread":"build-22"},{"duration":0,"stepId":"io.quarkus.arc.deployment.ObserverValidationProcessor#validateApplicationObserver","started":"16:00:56.971","dependents":[344],"id":334,"thread":"build-19"},{"duration":0,"stepId":"io.quarkus.devservices.h2.deployment.H2DevServicesProcessor#setupH2","started":"16:00:56.892","dependents":[293],"id":7,"thread":"build-3"},{"duration":0,"stepId":"io.quarkus.deployment.steps.CapabilityAggregationStep#aggregateCapabilities","started":"16:00:56.914","dependents":[350,241,240,242,283,177,182,306,193,180,231,273,285,282,223,179,265,360,181,178],"id":176,"thread":"build-2"},{"duration":0,"stepId":"io.quarkus.arc.deployment.ConfigBuildStep#validateConfigPropertiesInjectionPoints","started":"16:00:56.971","dependents":[339],"id":338,"thread":"build-13"},{"duration":0,"stepId":"io.quarkus.resteasy.reactive.server.deployment.ResteasyReactiveScanningProcessor#scanForContextResolvers","started":"16:00:56.920","dependents":[298,376,360,354,306],"id":261,"thread":"build-25"},{"duration":0,"stepId":"io.quarkus.deployment.dev.io.NioThreadPoolDevModeProcessor#setupTCCL","started":"16:00:56.900","dependents":[377],"id":91,"thread":"build-7"},{"duration":0,"stepId":"io.quarkus.hibernate.orm.deployment.HibernateOrmProcessor#enforceDisableRuntimeEnhancer","started":"16:00:56.895","dependents":[377],"id":53,"thread":"build-7"},{"duration":0,"stepId":"io.quarkus.arc.deployment.ArcProcessor#transformListAllInjectionPoints","started":"16:00:56.894","dependents":[306],"id":34,"thread":"build-8"},{"duration":0,"stepId":"io.quarkus.agroal.deployment.AgroalProcessor#agroal","started":"16:00:56.894","dependents":[377],"id":28,"thread":"build-10"},{"duration":0,"stepId":"io.quarkus.vertx.deployment.VertxProcessor#featureAndCapability","started":"16:00:56.895","dependents":[176,377],"id":41,"thread":"build-6"},{"duration":0,"stepId":"io.quarkus.resteasy.reactive.server.deployment.ResteasyReactiveProcessor#responseStatusSupport","started":"16:00:56.900","dependents":[350],"id":82,"thread":"build-6"},{"duration":0,"stepId":"io.quarkus.arc.deployment.ConfigBuildStep#warnStaticInitInjectionPoints","started":"16:00:56.971","dependents":[340],"id":335,"thread":"build-22"},{"duration":0,"stepId":"io.quarkus.resteasy.reactive.server.deployment.devconsole.ResteasyReactiveDevConsoleProcessor#paramConverterProviders","started":"16:00:56.914","dependents":[374],"id":186,"thread":"build-15"},{"duration":0,"stepId":"io.quarkus.resteasy.reactive.jackson.deployment.processor.ResteasyReactiveJacksonProcessor#jsonDefault","started":"16:00:56.917","dependents":[350],"id":209,"thread":"build-19"},{"duration":0,"stepId":"io.quarkus.resteasy.reactive.server.deployment.ResteasyReactiveScanningProcessor#scanForParamConverters_59e3169e3a646b7fcf3083416f558434b73816c5","started":"16:00:56.920","dependents":[259],"id":255,"thread":"build-11"},{"duration":0,"stepId":"io.quarkus.devservices.deployment.DevServicesProcessor#config","started":"16:00:56.935","dependents":[357,297],"id":296,"thread":"build-20"},{"duration":0,"stepId":"io.quarkus.resteasy.reactive.server.deployment.ResteasyReactiveProcessor#additionalAsyncTypeMethodScanners","started":"16:00:56.909","dependents":[350],"id":142,"thread":"build-14"},{"duration":0,"stepId":"io.quarkus.deployment.logging.LoggingResourceProcessor#setupStackTraceFormatter","started":"16:00:56.932","dependents":[292],"id":291,"thread":"build-21"},{"duration":0,"stepId":"io.quarkus.hibernate.orm.deployment.HibernateOrmCdiProcessor#registerAnnotations","started":"16:00:56.894","dependents":[298,190,306],"id":47,"thread":"build-7"},{"duration":0,"stepId":"io.quarkus.arc.deployment.HotDeploymentConfigBuildStep#configFile","started":"16:00:56.892","dependents":[286],"id":3,"thread":"build-3"},{"duration":0,"stepId":"io.quarkus.arc.deployment.BuildTimeEnabledProcessor#unlessBuildProfile","started":"16:00:56.918","dependents":[260,249,263],"id":228,"thread":"build-8"},{"duration":0,"stepId":"io.quarkus.deployment.pkg.steps.PackageTypeVerificationBuildStep#verify","started":"16:00:56.908","dependents":[372,374,373],"id":133,"thread":"build-12"},{"duration":0,"stepId":"io.quarkus.hibernate.orm.panache.deployment.PanacheHibernateResourceProcessor#marker","started":"16:00:56.908","dependents":[188],"id":136,"thread":"build-5"},{"duration":0,"stepId":"io.quarkus.deployment.console.ConsoleProcessor#quitCommand","started":"16:00:56.900","dependents":[357],"id":88,"thread":"build-5"},{"duration":0,"stepId":"io.quarkus.arc.deployment.ConfigBuildStep#validateConfigValues","started":"16:00:57.007","dependents":[376,377],"id":346,"thread":"build-20"},{"duration":0,"stepId":"io.quarkus.resteasy.reactive.server.deployment.ResteasyReactiveDevModeProcessor#addReactiveRoutesExceptionMapper","started":"16:00:56.899","dependents":[377],"id":70,"thread":"build-1"},{"duration":0,"stepId":"io.quarkus.deployment.steps.ConfigGenerationBuildStep#generateConfigClass","started":"16:00:56.971","dependents":[376],"id":336,"thread":"build-2"},{"duration":0,"stepId":"io.quarkus.deployment.logging.LoggingResourceProcessor#setupLogFilters","started":"16:00:56.900","dependents":[292,216],"id":93,"thread":"build-8"},{"duration":0,"stepId":"io.quarkus.arc.deployment.AutoProducerMethodsProcessor#annotationTransformer","started":"16:00:56.937","dependents":[306],"id":305,"thread":"build-20"},{"duration":0,"stepId":"io.quarkus.narayana.jta.deployment.NarayanaJtaProcessor#registerScope","started":"16:00:56.895","dependents":[52],"id":50,"thread":"build-6"},{"duration":0,"stepId":"io.quarkus.hibernate.orm.panache.deployment.PanacheHibernateResourceProcessor#build","started":"16:00:56.965","dependents":[369,377],"id":328,"thread":"build-4"},{"duration":0,"stepId":"io.quarkus.deployment.recording.substitutions.AdditionalSubstitutionsBuildStep#additionalSubstitutions","started":"16:00:56.908","dependents":[377],"id":138,"thread":"build-12"},{"duration":0,"stepId":"io.quarkus.vertx.http.deployment.VertxHttpProcessor#notFoundRoutes","started":"16:00:57.017","dependents":[363,364],"id":361,"thread":"build-25"},{"duration":0,"stepId":"io.quarkus.vertx.http.deployment.HttpSecurityProcessor#initMtlsClientAuth","started":"16:00:56.902","dependents":[317,320,323,377],"id":114,"thread":"build-7"},{"duration":0,"stepId":"io.quarkus.deployment.steps.RuntimeConfigSetupBuildStep#setupRuntimeConfig","started":"16:00:56.902","dependents":[292,278,174,120,119,368,240,373,141,122,375,182,125,367,115,165,160,175,114,365,116,377,348,362],"id":113,"thread":"build-11"},{"duration":0,"stepId":"io.quarkus.deployment.SslProcessor#setupNativeSsl","started":"16:00:56.910","dependents":[162,241,240,220],"id":161,"thread":"build-11"},{"duration":0,"stepId":"io.quarkus.deployment.steps.CapabilityAggregationStep#provideCapabilities","started":"16:00:56.910","dependents":[176],"id":158,"thread":"build-18"},{"duration":0,"stepId":"io.quarkus.resteasy.reactive.server.deployment.ResteasyReactiveScanningProcessor#scanForDynamicFeatures","started":"16:00:56.921","dependents":[360,268],"id":267,"thread":"build-13"},{"duration":0,"stepId":"io.quarkus.resteasy.reactive.server.deployment.ResteasyReactiveProcessor#additionalReflection","started":"16:00:57.010","dependents":[376],"id":358,"thread":"build-20"},{"duration":0,"stepId":"io.quarkus.vertx.http.deployment.VertxHttpProcessor#frameworkRoot","started":"16:00:56.908","dependents":[371,143,342,355,170,367,365,309],"id":134,"thread":"build-8"},{"duration":0,"stepId":"io.quarkus.netty.deployment.NettyProcessor#cleanup","started":"16:00:56.908","dependents":[292,216],"id":135,"thread":"build-7"},{"duration":0,"stepId":"io.quarkus.hibernate.orm.deployment.HibernateOrmProcessor#devServicesAutoGenerateByDefault","started":"16:00:56.924","dependents":[294],"id":279,"thread":"build-25"},{"duration":0,"stepId":"io.quarkus.hibernate.orm.panache.common.deployment.PanacheJpaCommonResourceProcessor#buildNamedQueryMap","started":"16:00:56.923","dependents":[377],"id":275,"thread":"build-13"},{"duration":0,"stepId":"io.quarkus.credentials.CredentialsProcessor#registerAdditionalBeans","started":"16:00:56.917","dependents":[298,306],"id":213,"thread":"build-24"},{"duration":0,"stepId":"io.quarkus.hibernate.orm.deployment.devconsole.HibernateDevConsoleProcessor#collectDeploymentUnits","started":"16:00:56.915","dependents":[374],"id":189,"thread":"build-2"},{"duration":0,"stepId":"io.quarkus.resteasy.reactive.jackson.deployment.processor.ResteasyReactiveJacksonProcessor#handleFieldSecurity","started":"16:00:57.009","dependents":[352],"id":351,"thread":"build-24"},{"duration":0,"stepId":"io.quarkus.deployment.steps.ConfigBuildSteps#generateConfigSources","started":"16:00:56.899","dependents":[],"id":62,"thread":"build-2"},{"duration":0,"stepId":"io.quarkus.vertx.http.deployment.VertxHttpProcessor#cors","started":"16:00:56.908","dependents":[367,377],"id":141,"thread":"build-4"},{"duration":0,"stepId":"io.quarkus.arc.deployment.BuildTimeEnabledProcessor#ifBuildProperty","started":"16:00:56.918","dependents":[260,249,263],"id":234,"thread":"build-4"},{"duration":0,"stepId":"io.quarkus.vertx.http.deployment.devmode.tests.TestsProcessor#forceRestart","started":"16:00:56.899","dependents":[371,309],"id":80,"thread":"build-12"},{"duration":0,"stepId":"io.quarkus.arc.deployment.ArcProcessor#feature","started":"16:00:56.900","dependents":[377],"id":81,"thread":"build-12"},{"duration":0,"stepId":"io.quarkus.deployment.recording.AnnotationProxyBuildStep#build","started":"16:00:56.910","dependents":[319],"id":166,"thread":"build-12"},{"duration":0,"stepId":"io.quarkus.vertx.core.deployment.VertxCoreProcessor#registerVerticleClasses","started":"16:00:56.919","dependents":[376],"id":245,"thread":"build-9"},{"duration":0,"stepId":"io.quarkus.arc.deployment.ArcProcessor#unremovableAsyncObserverExceptionHandlers","started":"16:00:56.899","dependents":[329],"id":66,"thread":"build-5"},{"duration":0,"stepId":"io.quarkus.hibernate.orm.deployment.HibernateOrmProcessor#enrollBeanValidationTypeSafeActivatorForReflection","started":"16:00:56.914","dependents":[376],"id":178,"thread":"build-12"},{"duration":0,"stepId":"io.quarkus.arc.deployment.LookupConditionsProcessor#suppressConditionsGenerators","started":"16:00:56.936","dependents":[306],"id":299,"thread":"build-20"},{"duration":0,"stepId":"io.quarkus.jackson.deployment.JacksonProcessor#autoRegisterModules","started":"16:00:56.919","dependents":[248],"id":244,"thread":"build-25"},{"duration":0,"stepId":"io.quarkus.hibernate.orm.panache.deployment.PanacheHibernateResourceProcessor#collectEntityClasses","started":"16:00:56.919","dependents":[328],"id":237,"thread":"build-24"},{"duration":0,"stepId":"io.quarkus.resteasy.reactive.server.deployment.ResteasyReactiveScanningProcessor#scanForExceptionMappers","started":"16:00:56.924","dependents":[298,376,360,306],"id":283,"thread":"build-15"},{"duration":0,"stepId":"io.quarkus.deployment.pkg.steps.FileSystemResourcesBuildStep#notNormalMode","started":"16:00:56.900","dependents":[],"id":102,"thread":"build-11"},{"duration":0,"stepId":"io.quarkus.vertx.http.deployment.devmode.console.ConfigEditorProcessor#handleRequests","started":"16:00:56.935","dependents":[371,309],"id":295,"thread":"build-21"},{"duration":0,"stepId":"io.quarkus.hibernate.orm.panache.deployment.PanacheHibernateResourceProcessor#ensureBeanLookupAvailable","started":"16:00:56.899","dependents":[329],"id":69,"thread":"build-9"},{"duration":0,"stepId":"io.quarkus.resteasy.reactive.jackson.deployment.processor.ResteasyReactiveJacksonProcessor#beans","started":"16:00:56.892","dependents":[298,306],"id":4,"thread":"build-1"},{"duration":0,"stepId":"io.quarkus.resteasy.reactive.server.deployment.ResteasyReactiveProcessor#securityExceptionMappers","started":"16:00:56.895","dependents":[283],"id":48,"thread":"build-3"},{"duration":0,"stepId":"io.quarkus.vertx.http.deployment.VertxHttpProcessor#filterMultipleVertxInstancesWarning","started":"16:00:56.917","dependents":[292,216],"id":205,"thread":"build-15"},{"duration":0,"stepId":"io.quarkus.arc.deployment.StartupBuildSteps#addScope","started":"16:00:56.899","dependents":[303],"id":61,"thread":"build-13"},{"duration":0,"stepId":"io.quarkus.deployment.logging.LoggingResourceProcessor#setUpDefaultLogCleanupFilters","started":"16:00:56.917","dependents":[340],"id":216,"thread":"build-7"},{"duration":0,"stepId":"io.quarkus.deployment.steps.MainClassBuildStep#mainClassBuildStep","started":"16:00:56.918","dependents":[],"id":227,"thread":"build-14"},{"duration":0,"stepId":"io.quarkus.mutiny.deployment.MutinyProcessor#buildTimeInit","started":"16:00:56.893","dependents":[377],"id":27,"thread":"build-7"},{"duration":0,"stepId":"io.quarkus.resteasy.reactive.server.deployment.ResteasyReactiveProcessor#buildSetup","started":"16:00:56.899","dependents":[377],"id":77,"thread":"build-5"},{"duration":0,"stepId":"io.quarkus.arc.deployment.LifecycleEventsBuildStep#startupEvent","started":"16:00:57.038","dependents":[375,377],"id":373,"thread":"build-10"},{"duration":0,"stepId":"io.quarkus.arc.deployment.CommandLineArgumentsProcessor#commandLineArgs","started":"16:00:56.917","dependents":[317,298,320,323,306],"id":211,"thread":"build-18"},{"duration":0,"stepId":"io.quarkus.arc.deployment.AutoAddScopeProcessor#annotationTransformer","started":"16:00:56.936","dependents":[329,306],"id":303,"thread":"build-20"},{"duration":0,"stepId":"io.quarkus.jackson.deployment.JacksonProcessor#unremovable","started":"16:00:56.918","dependents":[329],"id":223,"thread":"build-18"},{"duration":0,"stepId":"io.quarkus.hibernate.orm.deployment.HibernateOrmProcessor#registerHibernateOrmMetadataForCoreDialects","started":"16:00:56.895","dependents":[273],"id":45,"thread":"build-1"},{"duration":0,"stepId":"io.quarkus.hibernate.orm.deployment.HibernateOrmProcessor#includeArchivesHostingEntityPackagesInIndex","started":"16:00:56.900","dependents":[188],"id":99,"thread":"build-5"},{"duration":0,"stepId":"io.quarkus.resteasy.reactive.server.deployment.ResteasyReactiveDevModeProcessor#addAdditionalEndpointsExceptionMapper","started":"16:00:57.017","dependents":[377],"id":364,"thread":"build-29"},{"duration":0,"stepId":"io.quarkus.hibernate.orm.deployment.HibernateOrmProcessor#addPersistenceUnitAnnotationToIndex","started":"16:00:56.917","dependents":[221],"id":198,"thread":"build-20"},{"duration":0,"stepId":"io.quarkus.hibernate.orm.deployment.HibernateOrmCdiProcessor#validatePersistenceUnitExtensions","started":"16:00:56.971","dependents":[344],"id":337,"thread":"build-24"},{"duration":0,"stepId":"io.quarkus.deployment.ConstructorPropertiesProcessor#build","started":"16:00:56.919","dependents":[376],"id":238,"thread":"build-9"},{"duration":0,"stepId":"io.quarkus.vertx.http.deployment.HttpSecurityProcessor#initFormAuth","started":"16:00:56.902","dependents":[371,317,320,361,323,377,365],"id":115,"thread":"build-10"},{"duration":0,"stepId":"io.quarkus.deployment.dev.testing.TestTracingProcessor#startTesting","started":"16:00:56.909","dependents":[372,292,374,373],"id":144,"thread":"build-14"},{"duration":0,"stepId":"io.quarkus.narayana.jta.deployment.NarayanaJtaProcessor#build","started":"16:00:56.902","dependents":[298,376,377,306],"id":116,"thread":"build-5"},{"duration":0,"stepId":"io.quarkus.arc.deployment.StartupBuildSteps#unremovableBeans","started":"16:00:56.918","dependents":[329],"id":219,"thread":"build-23"},{"duration":0,"stepId":"io.quarkus.arc.deployment.ConfigBuildStep#registerConfigPropertiesBean","started":"16:00:56.958","dependents":[324],"id":312,"thread":"build-13"},{"duration":0,"stepId":"io.quarkus.deployment.DockerStatusProcessor#IsDockerWorking","started":"16:00:56.908","dependents":[293,296],"id":137,"thread":"build-8"},{"duration":0,"stepId":"io.quarkus.vertx.core.deployment.VertxCoreProcessor#filterNettyHostsFileParsingWarn","started":"16:00:56.893","dependents":[292,216],"id":14,"thread":"build-5"},{"duration":0,"stepId":"io.quarkus.hibernate.orm.panache.deployment.PanacheHibernateResourceProcessor#featureBuildItem","started":"16:00:56.895","dependents":[377],"id":44,"thread":"build-5"},{"duration":0,"stepId":"io.quarkus.jdbc.h2.deployment.JDBCH2Processor#feature","started":"16:00:56.917","dependents":[377],"id":197,"thread":"build-12"},{"duration":0,"stepId":"io.quarkus.resteasy.reactive.server.deployment.ResteasyReactiveCDIProcessor#pathInterfaceImpls","started":"16:00:56.920","dependents":[298,306],"id":253,"thread":"build-17"},{"duration":0,"stepId":"io.quarkus.vertx.core.deployment.VertxCoreProcessor#overrideContextInternalInterfaceToAddSafeGuards","started":"16:00:56.917","dependents":[369],"id":195,"thread":"build-13"},{"duration":0,"stepId":"io.quarkus.arc.deployment.ArcProcessor#setupExecutor","started":"16:00:56.908","dependents":[377],"id":127,"thread":"build-9"},{"duration":0,"stepId":"io.quarkus.resteasy.reactive.common.deployment.ResteasyReactiveCommonProcessor#handleApplication","started":"16:00:56.919","dependents":[261,350,256,267,349,376,283,255,359,251,257,360,280],"id":249,"thread":"build-5"},{"duration":0,"stepId":"io.quarkus.spring.di.deployment.SpringDIProcessor#registerFeature","started":"16:00:56.917","dependents":[377],"id":203,"thread":"build-7"},{"duration":0,"stepId":"io.quarkus.agroal.deployment.AgroalMetricsProcessor#registerMetrics","started":"16:00:56.918","dependents":[377],"id":218,"thread":"build-14"},{"duration":0,"stepId":"io.quarkus.arc.deployment.ConfigBuildStep#generateConfigClasses","started":"16:00:56.918","dependents":[335,313,333,312,376,338],"id":233,"thread":"build-11"},{"duration":0,"stepId":"io.quarkus.arc.deployment.staticmethods.InterceptedStaticMethodsProcessor#processInterceptedStaticMethods","started":"16:00:56.960","dependents":[369,376,326],"id":322,"thread":"build-15"},{"duration":0,"stepId":"io.quarkus.resteasy.reactive.server.deployment.ResteasyReactiveScanningProcessor#scanForInterceptors","started":"16:00:56.920","dependents":[280],"id":257,"thread":"build-19"},{"duration":0,"stepId":"io.quarkus.vertx.deployment.VertxProcessor#build","started":"16:00:56.959","dependents":[372,374,373,376,377],"id":319,"thread":"build-22"},{"duration":0,"stepId":"io.quarkus.resteasy.reactive.server.deployment.devconsole.ResteasyReactiveDevConsoleProcessor#collectAdditionalEndpoints","started":"16:00:57.017","dependents":[366],"id":363,"thread":"build-13"},{"duration":0,"stepId":"io.quarkus.panache.common.deployment.PanacheHibernateCommonResourceProcessor#replaceFieldAccesses","started":"16:00:56.965","dependents":[369],"id":327,"thread":"build-22"},{"duration":0,"stepId":"io.quarkus.deployment.logging.LoggingResourceProcessor#logConsoleCommand","started":"16:00:56.893","dependents":[357],"id":30,"thread":"build-5"},{"duration":0,"stepId":"io.quarkus.hibernate.orm.deployment.HibernateOrmAlwaysEnabledProcessor#featureBuildItem","started":"16:00:56.910","dependents":[377],"id":159,"thread":"build-19"},{"duration":0,"stepId":"io.quarkus.vertx.http.deployment.VertxHttpProcessor#openSocket","started":"16:00:57.038","dependents":[376,377],"id":375,"thread":"build-3"},{"duration":0,"stepId":"io.quarkus.netty.deployment.NettyProcessor#eagerlyInitClass","started":"16:00:56.893","dependents":[377],"id":12,"thread":"build-3"},{"duration":0,"stepId":"io.quarkus.arc.deployment.AutoInjectFieldProcessor#annotationTransformer","started":"16:00:56.936","dependents":[306],"id":302,"thread":"build-21"},{"duration":0,"stepId":"io.quarkus.resteasy.reactive.server.deployment.ResteasyReactiveScanningProcessor#cacheControlSupport","started":"16:00:56.900","dependents":[350],"id":83,"thread":"build-9"},{"duration":0,"stepId":"io.quarkus.vertx.http.deployment.devmode.tests.TestsProcessor#toggleLiveReloadEnabled","started":"16:00:56.894","dependents":[371,309],"id":38,"thread":"build-1"},{"duration":0,"stepId":"io.quarkus.arc.deployment.ArcProcessor#initialize","started":"16:00:56.937","dependents":[310,343,307],"id":306,"thread":"build-15"},{"duration":0,"stepId":"io.quarkus.deployment.steps.ApplicationInfoBuildStep#create","started":"16:00:56.901","dependents":[377],"id":108,"thread":"build-10"},{"duration":0,"stepId":"io.quarkus.vertx.deployment.VertxProcessor#registerBean","started":"16:00:56.900","dependents":[298,306],"id":105,"thread":"build-12"},{"duration":0,"stepId":"io.quarkus.deployment.ExtensionLoader#booleanSupplierFactory","started":"16:00:56.892","dependents":[158],"id":9,"thread":"build-5"},{"duration":0,"stepId":"io.quarkus.hibernate.orm.panache.deployment.PanacheHibernateResourceProcessor#validate","started":"16:00:56.971","dependents":[344],"id":332,"thread":"build-2"},{"duration":0,"stepId":"io.quarkus.deployment.logging.LoggingResourceProcessor#setUpDefaultLevels","started":"16:00:56.906","dependents":[292,340],"id":123,"thread":"build-4"},{"duration":0,"stepId":"io.quarkus.netty.deployment.NettyProcessor#registerEventLoopBeans","started":"16:00:56.910","dependents":[317,320,323,377],"id":168,"thread":"build-14"},{"duration":0,"stepId":"io.quarkus.hibernate.orm.deployment.HibernateOrmProcessor#handleNativeImageImportSql","started":"16:00:56.923","dependents":[341],"id":274,"thread":"build-25"},{"duration":0,"stepId":"io.quarkus.resteasy.reactive.server.deployment.ObservabilityProcessor#integrateObservability","started":"16:00:56.914","dependents":[350],"id":179,"thread":"build-20"},{"duration":0,"stepId":"io.quarkus.hibernate.orm.deployment.HibernateLogFilterBuildStep#setupLogFilters","started":"16:00:56.893","dependents":[292,216],"id":18,"thread":"build-7"},{"duration":0,"stepId":"io.quarkus.deployment.steps.BlockingOperationControlBuildStep#blockingOP","started":"16:00:56.894","dependents":[377],"id":39,"thread":"build-8"},{"duration":0,"stepId":"io.quarkus.vertx.http.deployment.StaticResourcesProcessor#runtimeInit","started":"16:00:57.007","dependents":[367,377],"id":348,"thread":"build-29"},{"duration":0,"stepId":"io.quarkus.hibernate.orm.deployment.HibernateOrmProcessor#pregenProxies","started":"16:00:57.031","dependents":[377],"id":370,"thread":"build-1"},{"duration":0,"stepId":"io.quarkus.deployment.pkg.steps.PackageTypeVerificationBuildStep#builtins","started":"16:00:56.900","dependents":[133],"id":85,"thread":"build-5"},{"duration":0,"stepId":"io.quarkus.resteasy.reactive.jackson.deployment.processor.ResteasyReactiveJacksonProcessor#feature","started":"16:00:56.917","dependents":[377],"id":196,"thread":"build-6"},{"duration":0,"stepId":"io.quarkus.vertx.core.deployment.VertxCoreProcessor#ioThreadDetector","started":"16:00:56.894","dependents":[377,39],"id":35,"thread":"build-7"},{"duration":0,"stepId":"io.quarkus.vertx.http.deployment.devmode.tests.TestsProcessor#printfailures","started":"16:00:56.900","dependents":[371,309],"id":95,"thread":"build-6"},{"duration":0,"stepId":"io.quarkus.hibernate.orm.deployment.HibernateOrmProcessor#warnOfSchemaProblems","started":"16:00:57.038","dependents":[377],"id":372,"thread":"build-1"},{"duration":0,"stepId":"io.quarkus.resteasy.reactive.server.deployment.ResteasyReactiveDevModeProcessor#addStaticResourcesExceptionMapper","started":"16:00:56.915","dependents":[377],"id":191,"thread":"build-24"},{"duration":0,"stepId":"io.quarkus.resteasy.reactive.common.deployment.ResteasyReactiveCommonProcessor#scanForIOInterceptors","started":"16:00:56.920","dependents":[280],"id":251,"thread":"build-10"},{"duration":0,"stepId":"io.quarkus.spring.di.deployment.SpringDIProcessor#beanTransformer","started":"16:00:56.936","dependents":[305,306],"id":304,"thread":"build-15"},{"duration":0,"stepId":"io.quarkus.vertx.http.deployment.VertxHttpProcessor#initializeRouter","started":"16:00:57.017","dependents":[367,377],"id":365,"thread":"build-14"},{"duration":0,"stepId":"io.quarkus.deployment.steps.DevServicesConfigBuildStep#deprecated","started":"16:00:56.892","dependents":[294],"id":1,"thread":"build-1"},{"duration":0,"stepId":"io.quarkus.vertx.http.deployment.VertxHttpProcessor#logging","started":"16:00:56.895","dependents":[123],"id":43,"thread":"build-1"},{"duration":0,"stepId":"io.quarkus.resteasy.reactive.server.deployment.ResteasyReactiveProcessor#registerCustomExceptionMappers","started":"16:00:56.899","dependents":[277],"id":68,"thread":"build-14"},{"duration":0,"stepId":"io.quarkus.hibernate.orm.deployment.HibernateOrmProcessor#hotDeploymentWatchedFiles","started":"16:00:56.899","dependents":[286],"id":57,"thread":"build-3"},{"duration":0,"stepId":"io.quarkus.vertx.http.deployment.devmode.tests.TestsProcessor#handleTestStatus","started":"16:00:56.918","dependents":[371,309],"id":215,"thread":"build-14"},{"duration":0,"stepId":"io.quarkus.vertx.http.deployment.devmode.console.DevConsoleProcessor#handler","started":"16:00:56.910","dependents":[292,377,309],"id":173,"thread":"build-15"},{"duration":0,"stepId":"io.quarkus.deployment.steps.ReflectionDiagnosticProcessor#writeReflectionData","started":"16:00:57.038","dependents":[],"id":376,"thread":"build-24"},{"duration":0,"stepId":"io.quarkus.caffeine.deployment.CaffeineProcessor#cacheLoaders","started":"16:00:56.918","dependents":[376],"id":232,"thread":"build-17"},{"duration":0,"stepId":"io.quarkus.resteasy.reactive.server.deployment.ResteasyReactiveDevModeProcessor#setupExceptionMapper","started":"16:00:56.910","dependents":[277,377],"id":169,"thread":"build-1"},{"duration":0,"stepId":"io.quarkus.hibernate.orm.deployment.HibernateUserTypeProcessor#build","started":"16:00:56.919","dependents":[376],"id":243,"thread":"build-15"},{"duration":0,"stepId":"io.quarkus.vertx.http.deployment.VertxHttpProcessor#shouldNotRemoveHttpServerOptionsCustomizers","started":"16:00:56.900","dependents":[329],"id":87,"thread":"build-11"}],"started":"2022-09-23T16:00:56.892","buildTarget":"rest-api-quarkus-1.0.0-SNAPSHOT"}